MANIFEST.in
setup.py
playlist_dl/Playlist.py
playlist_dl/Video.py
playlist_dl/__init__.py
playlist_dl/playlist_dl.py
playlist_dl.egg-info/PKG-INFO
playlist_dl.egg-info/SOURCES.txt
playlist_dl.egg-info/dependency_links.txt
playlist_dl.egg-info/entry_points.txt
playlist_dl.egg-info/not-zip-safe
playlist_dl.egg-info/requires.txt
playlist_dl.egg-info/top_level.txt