Metadata-Version: 1.1
Name: playlist-dl
Version: 0.2
Summary: Configurable Youtube Playlist downloader
Home-page: http://github.com/aviaryan/playlist-dl
Author: Avi Aryan
Author-email: avi.aryan123@gmail.com
License: Apache
Keywords: youtube playlist download youtube-dl ytd
Platform: UNKNOWN
Classifier: Development Status :: 4 - Beta
Classifier: Topic :: Utilities
Classifier: License :: OSI Approved :: Apache Software License
Classifier: Programming Language :: Python :: 3
Classifier: Programming Language :: Python :: 3.0
Classifier: Programming Language :: Python :: 3.1
Classifier: Programming Language :: Python :: 3.2
Classifier: Programming Language :: Python :: 3.3
Classifier: Programming Language :: Python :: 3.4
Classifier: Programming Language :: Python :: 3.5
Classifier: Programming Language :: Python :: 3 :: Only
